goto/__init__.py
goto/cli.py
goto/config.py
goto/install.py
goto/storage.py
goto/util.py
goto/shell/goto
goto/shell/goto-bash.sh
goto/shell/goto-zsh.sh
goto_cd-0.1.1.dist-info/LICENSE
goto_cd-0.1.1.dist-info/METADATA
goto_cd-0.1.1.dist-info/WHEEL
goto_cd-0.1.1.dist-info/entry_points.txt
goto_cd-0.1.1.dist-info/top_level.txt
goto_cd-0.1.1.dist-info/RECORD
