Metadata-Version: 2.1
Name: goto-cd
Version: 0.1.1
Summary: Teleport to anywhere on your computer
Home-page: https://github.com/catears/goto
Author: Henke Adolfsson
Author-email: catears13@gmail.com
License: UNKNOWN
Platform: UNKNOWN
Classifier: Development Status :: 3 - Alpha
Classifier: Environment :: Console
Classifier: Intended Audience :: Developers
Classifier: License :: OSI Approved :: MIT License
Classifier: Operating System :: Unix
Classifier: Programming Language :: Python :: 3
Classifier: Programming Language :: Python :: 2
Classifier: Topic :: System :: Shells
Requires-Dist: toml
Requires-Dist: click
